Metadata-Version: 2.1
Name: watero-go
Version: 0.1
Summary: 采集节点数据并上报Watero Center，同时接收Watero Center推送的控制信息
Home-page: https://github.com/Qinnnnnn/Watero_Go
Author: Clever Moon
Author-email: qzr19970105@live.com
License: UNKNOWN
Platform: UNKNOWN
Classifier: Programming Language :: Python :: 3
Classifier: License :: OSI Approved :: MIT License
Classifier: Operating System :: OS Independent
